nornflow/__init__.py
nornflow/builder.py
nornflow/catalogs.py
nornflow/constants.py
nornflow/exceptions.py
nornflow/logger.py
nornflow/nornflow.py
nornflow/nornir_manager.py
nornflow/settings.py
nornflow/utils.py
nornflow/blueprints/__init__.py
nornflow/blueprints/expander.py
nornflow/blueprints/resolver.py
nornflow/builtins/__init__.py
nornflow/builtins/filters.py
nornflow/builtins/tasks.py
nornflow/builtins/utils.py
nornflow/builtins/hooks/__init__.py
nornflow/builtins/hooks/if_hook.py
nornflow/builtins/hooks/set_to.py
nornflow/builtins/hooks/shush.py
nornflow/builtins/jinja2_filters/__init__.py
nornflow/builtins/jinja2_filters/custom_filters.py
nornflow/builtins/jinja2_filters/py_wrapper_filters.py
nornflow/builtins/processors/__init__.py
nornflow/builtins/processors/decorators.py
nornflow/builtins/processors/default_processor.py
nornflow/builtins/processors/failure_strategy_processor.py
nornflow/builtins/processors/hook_processor.py
nornflow/cli/__init__.py
nornflow/cli/constants.py
nornflow/cli/entrypoint.py
nornflow/cli/exceptions.py
nornflow/cli/init.py
nornflow/cli/run.py
nornflow/cli/show.py
nornflow/cli/samples/defaults.yaml
nornflow/cli/samples/greet_user.py
nornflow/cli/samples/hello_world.py
nornflow/cli/samples/hello_world.yaml
nornflow/cli/samples/nornflow.yaml
nornflow/cli/samples/nornir_configs/config.yaml
nornflow/cli/samples/nornir_configs/defaults.yaml
nornflow/cli/samples/nornir_configs/groups.yaml
nornflow/cli/samples/nornir_configs/hosts.yaml
nornflow/hooks/__init__.py
nornflow/hooks/base.py
nornflow/hooks/exceptions.py
nornflow/hooks/loader.py
nornflow/hooks/mixins.py
nornflow/j2/__init__.py
nornflow/j2/constants.py
nornflow/j2/core.py
nornflow/j2/exceptions.py
nornflow/models/__init__.py
nornflow/models/base.py
nornflow/models/blueprint.py
nornflow/models/hookable.py
nornflow/models/task.py
nornflow/models/validators.py
nornflow/models/workflow.py
nornflow/vars/__init__.py
nornflow/vars/constants.py
nornflow/vars/context.py
nornflow-0.7.0.dist-info/METADATA
nornflow-0.7.0.dist-info/WHEEL
nornflow-0.7.0.dist-info/entry_points.txt
nornflow-0.7.0.dist-info/licenses/LICENSE
nornflow-0.7.0.dist-info/RECORD
