Metadata-Version: 2.4
Name: nornflow
Version: 0.7.0
Summary: A workflow orchestration tool for network automation built around Nornir.
Author: Andre Lima
License: GPL-3.0-or-later
License-File: LICENSE
Requires-Python: >=3.10
Requires-Dist: jmespath>=1.0.1
Requires-Dist: nornir-utils>=0.2.0
Requires-Dist: nornir>=3.5.0
Requires-Dist: pydantic-serdes>=1.0.4
Requires-Dist: pydantic-settings>=2.12.0
Requires-Dist: pytest>=8.3.4
Requires-Dist: pyyaml>=6.0.2
Requires-Dist: tabulate>=0.9.0
Requires-Dist: termcolor>=2.5.0
Requires-Dist: typer>=0.15.1
Provides-Extra: dev
Requires-Dist: black>=25.12.0; extra == 'dev'
Requires-Dist: mypy>=1.15.0; extra == 'dev'
Requires-Dist: pytest-cov>=6.0.0; extra == 'dev'
Requires-Dist: ruff>=0.14.10; extra == 'dev'
Provides-Extra: manual-tests
Requires-Dist: nornir-napalm>=0.5.0; extra == 'manual-tests'
Requires-Dist: nornir-nautobot>=4.0.0; extra == 'manual-tests'
Requires-Dist: nornir-netbox>=0.3.0; extra == 'manual-tests'
Requires-Dist: nornir-netmiko>=1.0.1; extra == 'manual-tests'
